Workbook

Sheet Overview
A1: Equity Analysis - Apple Inc.

Sheet Financials
A1: Financials | B1: Revenue | C1: Net Income | D1: Total Assets | E1: Total Liabilities | F1: Equity
A2: 2020 | B2: 274515 | C2: 57411 | D2: 323888 | E2: 258549 | F2: =Table2[[#This Row],[Total Assets]]-Table2[[#This Row],[Total Liabilities]] -> 65339
A3: 2021 | B3: 365817 | C3: 94680 | D3: 351002 | E3: 287912 | F3: =Table2[[#This Row],[Total Assets]]-Table2[[#This Row],[Total Liabilities]] -> 63090
A4: 2022 | B4: 394328 | C4: 99803 | D4: 352755 | E4: 302083 | F4: =Table2[[#This Row],[Total Assets]]-Table2[[#This Row],[Total Liabilities]] -> 50672
A5: 2023 | B5: 383285 | C5: 96995 | D5: 352583 | E5: 290437 | F5: =Table2[[#This Row],[Total Assets]]-Table2[[#This Row],[Total Liabilities]] -> 62146
A6: 2024 | B6: 391035 | C6: 93736 | D6: 364980 | E6: 308030 | F6: =Table2[[#This Row],[Total Assets]]-Table2[[#This Row],[Total Liabilities]] -> 56950

Sheet Ratios
A1: Year | B1: Revenue Growth | C1: Net Profit Margin | D1: ROE | E1: Debt to Equity
A2: 2020
A3: 2021 | B3: =(Financials!B3/Financials!B2) - 1 -> 0.33259385 | C3: =(Financials!C2/Financials!B2) -> 0.20913611 | D3: =(Financials!C2/Financials!F2) -> 0.87866359 | E3: =(Financials!E3/Financials!F2) -> 4.4064341
A4: 2022 | B4: =(Financials!B4/Financials!B3) - 1 -> 0.077937876 | C4: =(Financials!C3/Financials!B3) -> 0.25881793 | D4: =(Financials!C3/Financials!F3) -> 1.5007133 | E4: =(Financials!E4/Financials!F3) -> 4.7881281
A5: 2023 | B5: =(Financials!B5/Financials!B4) - 1 -> -0.028004605 | C5: =(Financials!C4/Financials!B4) -> 0.25309641 | D5: =(Financials!C4/Financials!F4) -> 1.9695887 | E5: =(Financials!E5/Financials!F4) -> 5.7317059
A6: 2024 | B6: =(Financials!B6/Financials!B5) - 1 -> 0.020219941 | C6: =(Financials!C5/Financials!B5) -> 0.25306234 | D6: =(Financials!C5/Financials!F5) -> 1.5607601 | E6: =(Financials!E6/Financials!F5) -> 4.9565539

Sheet Dashboard
